_pyogmaneo.so
pyogmaneo.py
pyogmaneo-1.0.3.dist-info/LICENSE.md
pyogmaneo-1.0.3.dist-info/METADATA
pyogmaneo-1.0.3.dist-info/WHEEL
pyogmaneo-1.0.3.dist-info/top_level.txt
pyogmaneo-1.0.3.dist-info/RECORD
