Metadata-Version: 2.1
Name: pyogmaneo
Version: 1.0.3
Summary: Python bindings for the OgmaNeo2 library
Home-page: https://ogmacorp.com/
Author: Ogma Intelligent Systems Corp
Author-email: info@ogmacorp.com
License: Creative Commons Attribution-NonCommercial-ShareAlike 4.0 International License
Platform: UNKNOWN
Classifier: Development Status :: 5 - Production/Stable
Classifier: Environment :: Console
Classifier: Intended Audience :: Science/Research
Classifier: License :: Other/Proprietary License
Classifier: Operating System :: POSIX :: Linux
Classifier: Programming Language :: Python
Classifier: Topic :: Scientific/Engineering :: Artificial Intelligence
Classifier: Topic :: Software Development :: Libraries :: Python Modules
